atropylib/__init__.py
atropylib/py.typed
atropylib/errors/__init__.py
atropylib/pubsub/message.py
atropylib/pubsub/nats_client.py
atropylib/telemetry/metrics.py
atropylib/telemetry/traces.py
atropylib/telemetry/utils.py
atropylib/telemetry/logs/__init__.py
atropylib/telemetry/logs/line_fix_handler.py
atropylib/telemetry/logs/uvicorn.py
atropylib-0.0.14.dist-info/METADATA
atropylib-0.0.14.dist-info/WHEEL
atropylib-0.0.14.dist-info/RECORD
